<!-- German text files -->
<ger>
	<!-- Jane Text -->
	<!-- Bath Scene -->
	<jane_bath_1>Was passiert hier...? Oh mein Gott was ist hier los? Wasser... ich brauche Wasser!</jane_bath_1>
	<jane_bath_2>Okay, ganz ruhig bleiben. Jetzt bloß keine Panik. Wer bist du, Frau im Spiegel? Bist du ich?\nVerdammt warum erkenne ich dich nicht?! Mir ist so heiß...</jane_bath_2>
	<jane_bath_3>Was zum…?! O-Oh mein… Nein, das ist… das ist Blut!!! Nicht mein Blut!\nWas ist denn hier los - oh Gott was habe ich getan?!</jane_bath_3>
	<jane_bath_4>Pat Rutherford. Z.31. 12:30 Uhr… Wer ist Pat Rutherford? War ich um 12:30 bei dieser oder diesem Pat?\nWar das heute? Was war heute? Was war gestern? WER BIN ICH?</jane_bath_4>
	<jane_bath_5>Nein... ich könnte doch nicht... nein bitte, ich habe doch nicht einen Mord begangen?!</jane_bath_5>
	
	<!-- House First Scene -->
	<jane_house_1_1>Es fühlt sich nicht an wie ein Zuhause...</jane_house_1_1>
	<jane_house_1_2>Naja, wenn du meinst...</jane_house_1_2>
	<jane_house_1_3>Was ist mit deinem Kopf?</jane_house_1_3>
	<jane_house_1_4>Ich sollte vorsichtig nachhaken woher die Narbe kommt...</jane_house_1_4>
	<jane_house_1_5>Ich hatte mich nur gefragt...</jane_house_1_5>
	<jane_house_1_6>Ok, ok!</jane_house_1_6>
	
	<!-- Michael Text -->
	<!--  House First Scene -->
	<michael_house_1_1>Willkommen zu Hause, Jane!</michael_house_1_1>
	<michael_house_1_2>Lass dir bisschen Zeit, du musst dich erst noch an alles gewöhnen,/nund wenn deine Erinnerungen wieder da sind, gibt sich das von selbst.</michael_house_1_2>
	<michael_house_1_3>Schau dich einfach um, vielleicht erinnerst du dich sogar an etwas.</michael_house_1_3>
	<michael_house_1_4>Das ist das Esszimmer./nWir haben hier oft mit Freunden gegessen.</michael_house_1_4>
	<michael_house_1_5>Das? Nur eine Verletzung, nichts schlimmes./nEs verheilt recht gut.</michael_house_1_5>
	<michael_house_1_6>Warum starrst du so? ... Die Narbe?</michael_house_1_6>
	<michael_house_1_7>Ok ich packe aus. Es war ein Badunfall, einer von der peinlichen Sorte. Bitte zwing mich nicht, das näher zu erläutern.</michael_house_1_7>
</ger>